ecrire/__init__.py
ecrire/ecrire.py
ecrire-0.1.0.dist-info/METADATA
ecrire-0.1.0.dist-info/WHEEL
ecrire-0.1.0.dist-info/top_level.txt
ecrire-0.1.0.dist-info/RECORD
