Metadata-Version: 2.4
Name: ecrire
Version: 0.1.0
Summary: fonction ecrire au lieu de print
Author: Adam Joliclerc
License: MIT
Requires-Python: >=3.10
